goodpoints/__init__.py
goodpoints/compress.py
goodpoints/compressc.c
goodpoints/compressc.cpython-313-darwin.so
goodpoints/compressc.pyx
goodpoints/ctt.py
goodpoints/cttc.c
goodpoints/cttc.cpython-313-darwin.so
goodpoints/cttc.pyx
goodpoints/gaussianc.c
goodpoints/gaussianc.cpython-313-darwin.so
goodpoints/gaussianc.pxd
goodpoints/gaussianc.pyx
goodpoints/herding.py
goodpoints/kt.py
goodpoints/ktc.c
goodpoints/ktc.cpython-313-darwin.so
goodpoints/ktc.pxd
goodpoints/ktc.pyx
goodpoints/sobolevc.c
goodpoints/sobolevc.cpython-313-darwin.so
goodpoints/sobolevc.pxd
goodpoints/sobolevc.pyx
goodpoints/tictoc.py
goodpoints/util.py
goodpoints/jax/__init__.py
goodpoints/jax/amd.py
goodpoints/jax/autotune.py
goodpoints/jax/chol_thin.py
goodpoints/jax/compress.py
goodpoints/jax/distribution.py
goodpoints/jax/dot.py
goodpoints/jax/dtc.py
goodpoints/jax/kt.py
goodpoints/jax/kt_swap_ls.py
goodpoints/jax/lr_debias.py
goodpoints/jax/lr_matrix.py
goodpoints/jax/mmd.py
goodpoints/jax/noop_debias.py
goodpoints/jax/pd.py
goodpoints/jax/recomb_thin.py
goodpoints/jax/reopt.py
goodpoints/jax/rounding.py
goodpoints/jax/rpc.py
goodpoints/jax/sliceable_points.py
goodpoints/jax/st.py
goodpoints/jax/std_thin.py
goodpoints/jax/kernel/__init__.py
goodpoints/jax/kernel/neg_euclidean.py
goodpoints/jax/kernel/precond_stein.py
goodpoints/jax/kernel/scalar.py
goodpoints/jax/kernel/sobol.py
goodpoints/jax/serial/__init__.py
goodpoints/jax/serial/cache_factory.py
goodpoints/jax/serial/dummy_cache.py
goodpoints/jax/serial/h5.py
goodpoints/jax/serial/mongodb_cache.py
goodpoints-0.4.1.dist-info/licenses/LICENSE
goodpoints-0.4.1.dist-info/METADATA
goodpoints-0.4.1.dist-info/WHEEL
goodpoints-0.4.1.dist-info/top_level.txt
goodpoints-0.4.1.dist-info/RECORD
