Metadata-Version: 2.4
Name: goodpoints
Version: 0.4.1
Summary: Tools to generate concise high-quality summaries of a probability distribution
Home-page: https://github.com/microsoft/goodpoints
License-File: LICENSE
Requires-Dist: numpy
Dynamic: license-file
